pytanksim/__init__.py
pytanksim/classes/__init__.py
pytanksim/classes/basesimclass.py
pytanksim/classes/excessisothermclass.py
pytanksim/classes/fluidsorbentclasses.py
pytanksim/classes/onephasefluidsimclasses.py
pytanksim/classes/onephasesorbentsimclasses.py
pytanksim/classes/simresultsclass.py
pytanksim/classes/storagetankclasses.py
pytanksim/classes/twophasefluidsimclasses.py
pytanksim/classes/twophasesorbentsimclasses.py
pytanksim/core/__init__.py
pytanksim/core/simulationgenerator.py
pytanksim/utils/__init__.py
pytanksim/utils/finitedifferences.py
pytanksim/utils/logging.py
pytanksim-1.1.2.dist-info/COPYING.LESSER.txt
pytanksim-1.1.2.dist-info/COPYING.txt
pytanksim-1.1.2.dist-info/METADATA
pytanksim-1.1.2.dist-info/NOTICE.txt
pytanksim-1.1.2.dist-info/WHEEL
pytanksim-1.1.2.dist-info/top_level.txt
pytanksim-1.1.2.dist-info/RECORD
