Metadata-Version: 2.1
Name: pytanksim
Version: 1.1.2
Summary: Simulates thermodynamics of fluid tank refueling and discharging.
Author: Muhammad Irfan Maulana Kusdhany
Author-email: ikusdhany@kyudai.jp
License: GNU Lesser General Public License v3 or later (LGPLv3+)
Project-URL: Homepage, https://github.com/nightynighto/pytanksim
Project-URL: Issues, https://github.com/nightynighto/pytanksim/issues
Keywords: hydrogen,methane,co2,adsorption,fluid,storage,porous,sorbent,thermodynamics
Classifier: Development Status :: 4 - Beta
Classifier: Intended Audience :: Science/Research
Classifier: Topic :: Scientific/Engineering :: Chemistry
Classifier: License :: OSI Approved :: GNU Lesser General Public License v3 or later (LGPLv3+)
Classifier: Programming Language :: Python :: 3.7
Requires-Python: >=3.7
License-File: NOTICE.txt
License-File: COPYING.txt
License-File: COPYING.LESSER.txt
Requires-Dist: scipy
Requires-Dist: numpy
Requires-Dist: pandas
Requires-Dist: matplotlib
Requires-Dist: tqdm
Requires-Dist: assimulo
Requires-Dist: lmfit
Requires-Dist: CoolProp
Provides-Extra: validation
Requires-Dist: SciencePlots ; extra == 'validation'
